ocr_utils/__init__.py
ocr_utils/alto_to_svg.py
ocr_utils/commons.py
ocr_utils/pdf_to_svg.py
ocr_utils/table.py
tesseract_ocr_utils-0.0.6.dist-info/LICENSE
tesseract_ocr_utils-0.0.6.dist-info/METADATA
tesseract_ocr_utils-0.0.6.dist-info/WHEEL
tesseract_ocr_utils-0.0.6.dist-info/top_level.txt
tesseract_ocr_utils-0.0.6.dist-info/RECORD
